hatch_modulefile/__about__.py
hatch_modulefile/__init__.py
hatch_modulefile/hooks.py
hatch_modulefile/inputs.py
hatch_modulefile/plugins.py
hatch_modulefile-0.1.1.dist-info/METADATA
hatch_modulefile-0.1.1.dist-info/WHEEL
hatch_modulefile-0.1.1.dist-info/entry_points.txt
hatch_modulefile-0.1.1.dist-info/licenses/LICENSE.txt
hatch_modulefile-0.1.1.dist-info/RECORD
