Metadata-Version: 2.1
Name: hatch-modulefile
Version: 0.1.1
Summary: Hatch plugin for use in Modulefiles environments
Project-URL: Documentation, https://github.com/rvandezande/hatch-modulefile#readme
Project-URL: Issues, https://github.com/rvandezande/hatch-modulefile/issues
Project-URL: Source, https://github.com/rvandezande/hatch-modulefile
Author-email: Reuben Vandezande <reuben.vandezande@gmail.com>
License-Expression: MIT
License-File: LICENSE.txt
Keywords: build,hatch,modulefiles,plugin,pth
Classifier: Development Status :: 4 - Beta
Classifier: Framework :: Hatch
Classifier: Programming Language :: Python
Classifier: Programming Language :: Python :: 3.7
Classifier: Programming Language :: Python :: 3.11
Requires-Python: >=3.7
Requires-Dist: hatchling>=1.6.0
